verilog/74670/hct74670.v
// https://media.digikey.com/pdf/Data%20Sheets/NXP%20PDFs/74HC(T)670.pdf
// active low enable inputs

// NOTE:
// MIN _WE pulsewidth = 20ns   : http://www.ti.com/lit/ds/schs195c/schs195c.pdf?ts=1588009560263
// MIN _WE pulsewidth = 9-18ns : https://media.digikey.com/pdf/Data%20Sheets/NXP%20PDFs/74HC(T)670.pdf

`timescale 1ns/1ns
module hct74670 (input _wr_en,
                 input [1:0] wr_addr,
                 input [3:0] wr_data,
                 input _rd_en,
                 input [1:0] rd_addr,
                 output [3:0] rd_data);
    
    parameter LOG=0;

    localparam PD_RE_TO_Q=18;
    localparam PD_A_TO_Q=21;
    localparam PD_D_TO_Q=27;
    localparam PD_WE_TO_Q=28;

// verilator lint_off UNOPTFLAT
    // Register file storage
    reg [3:0] registers[3:0];
    reg [3:0] tmp_data;

// verilator lint_on UNOPTFLAT

    // necessary to make it possible to set an initial value into REGA so that I can do   NAME=0   
    // or any other operation without X into an ALU input causing an X on the output
    initial begin
        if (LOG) $display("INITIALISING EMPTY REGISTER %m FILE TO VALUES [0,1,2,3]");
        registers[0] = 0;
        registers[1] = 1;
        registers[2] = 2;
        registers[3] = 3;
    end
      
    reg [3:0] out_val;
    
    specify
        (_rd_en *> rd_data)  = PD_RE_TO_Q;
        (_wr_en *> rd_data)  = PD_WE_TO_Q;
        (rd_addr *> rd_data) = PD_A_TO_Q;
        (wr_data => rd_data) = PD_D_TO_Q;
    endspecify
    
    // write to register file
    always @* begin
        if (!_wr_en) begin
            registers[wr_addr] = wr_data;
        end
    end

    always @(registers[0]) begin
            if (LOG) $display("%9t ", $time, ": 74670 setting reg[0]  <= ", registers[0], " : %m");
    end
    always @(registers[1]) begin
            if (LOG) $display("%9t ", $time, ": 74670 setting reg[1]  <= ", registers[1], " : %m");
    end
    always @(registers[2]) begin
            if (LOG) $display("%9t ", $time, ": 74670 setting reg[2]  <= ", registers[2], " : %m");
    end
    always @(registers[3]) begin
            if (LOG) $display("%9t ", $time, ": 74670 setting reg[3]  <= ", registers[3], " : %m");
    end
        
        
    // reading from register file
    always_comb
    // always @(*)  << this gives warning: ./hct74670.v:32: warning: @* is sensitive to all 4 words in array 'registers'.
    begin
        out_val = registers[rd_addr];
    end
    
    assign rd_data = _rd_en ? 4'bz : out_val;
    
endmodule

verilog/registerFile/registerFile.v
`ifndef  V_RF
`define  V_RF


/* 4x8 dual port register file
 */

`include "../74670/hct74670.v"
//`include "../pulseGenerator/pulseGenerator.v"
`timescale 1ns/1ns
module registerFile #(parameter LOG=0) (
                    input _wr_en, 
                    input [1:0] wr_addr,
                    input [7:0] wr_data,

                    input _rdA_en,
                    input [1:0] rdA_addr,
                    output [7:0] rdA_data,

                    input _rdB_en,
                    input [1:0] rdB_addr,
                    output [7:0] rdB_data
	    );

    
    wire [3:0] wr_data_hi, wr_data_lo;
// verilator lint_off UNOPTFLAT
    wire [3:0] rdA_data_hi, rdA_data_lo, rdB_data_hi, rdB_data_lo;
// verilator lint_on UNOPTFLAT

    assign {wr_data_hi, wr_data_lo} = wr_data;
    assign rdA_data                 = {rdA_data_hi, rdA_data_lo};
    assign rdB_data                 = {rdB_data_hi, rdB_data_lo};

    hct74670 bankA_lo(
        _wr_en,
        wr_addr,
        wr_data_lo,
        _rdA_en,
        rdA_addr,
        rdA_data_lo
    );
    hct74670 bankA_hi(
        _wr_en,
        wr_addr,
        wr_data_hi,
        _rdA_en,
        rdA_addr,
        rdA_data_hi
    );
    
    hct74670 bankB_lo(
        _wr_en,
        wr_addr,
        wr_data_lo,
        _rdB_en,
        rdB_addr,
        rdB_data_lo
    );
    hct74670 bankB_hi(
        _wr_en,
        wr_addr,
        wr_data_hi,
        _rdB_en,
        rdB_addr,
        rdB_data_hi
    );
    
    if (LOG) always @(negedge _wr_en) begin 
        $display("%9t REGFILE : BEGIN WRITE _wr_en=%1b,  write[%d]=%-3d     _rdX_en=%1b, X[%d]=>%-3d    _rdY_en=%1b, Y[%d]=>%-3d" , $time, 
                    _wr_en, wr_addr, wr_data, 
                    _rdA_en, rdA_addr, rdA_data, 
                    _rdA_en, rdB_addr, rdB_data);
    end
    if (LOG) always @(posedge _wr_en) begin 
        $display("%9t REGFILE : END WRITE _wr_en=%1b,  write[%d]=%-3d     _rdX_en=%1b, X[%d]=>%-3d    _rdY_en=%1b, Y[%d]=>%-3d" , $time, 
                    _wr_en, wr_addr, wr_data, 
                    _rdA_en, rdA_addr, rdA_data, 
                    _rdA_en, rdB_addr, rdB_data);
    end

    function [7:0] get([1:0] r);
        get = {bankA_hi.registers[r], bankA_lo.registers[r]};
    endfunction

    // only need to bind to L or R as they have the same value
    if (LOG) always @(   
                    _wr_en//, wr_addr, wr_data, 
                    //_rdA_en, rdA_addr, rdA_data, 
                    //_rdA_en, rdB_addr, rdB_data
    ) begin
        $display("%9t ", $time, "REGFILE : _wr_en=%1b", //,  write[%d]=%-3d     _rdX_en=%1b, X[%d]=>%-3d    _rdY_en=%1b, Y[%d]=>%-3d" , 
                    _wr_en//, wr_addr, wr_data, 
                    //_rdA_en, rdA_addr, rdA_data, 
                    //_rdA_en, rdB_addr, rdB_data
                    );
    end

`ifndef verilator
    if (LOG) always @(   
                bankB_hi.registers[0] or bankB_lo.registers[0] or
                bankB_hi.registers[1] or bankB_lo.registers[1] or
                bankB_hi.registers[2] or bankB_lo.registers[2] or
                bankB_hi.registers[3] or bankB_lo.registers[3]
    ) begin
        $display("%9t ", $time, "REGFILE : DATA UPDATE A=%-3d(%-2x) B=%-3d(%-2x) C=%-3d(%-2x) D=%-3d(%-2x)", 
                get(0), get(0), 
                get(1), get(1), 
                get(2), get(2), 
                get(3), get(3));
    end
`endif

/*
    if (LOG) always @(posedge _wr_en) begin
        $display("%8d REGFILE-A : _wr_en +vs edge - STORING write[%d] = %d", $time, wr_addr, wr_data);
    end
*/
    
endmodule

`endif

verilog/74574/hct74574.v
/* Timings from https://assets.nexperia.com/documents/data-sheet/74HC_HCT574.pdf
 * */
`timescale 1ns/100ps
module hct74574 (
input CLK,
input OE_N,        // negative enable
input [7:0] D,
output [7:0] Q
);
    reg [8:0] data;
    
    specify
    (CLK *> Q) = (15);
    (OE_N *> Q) = (19);
    endspecify
    
    always @(posedge CLK)
        data <= D;
    
    assign #(19) Q = OE_N ? 8'bz: data;
    
endmodule

verilog/registerFile/syncRegisterFile.v
/* 4x8 dual port register file
* latches write data on postive edge, all other inputs remain async.
 */

`include "../registerFile/registerFile.v"
`include "../74574/hct74574.v"
`timescale 1ns/100ps
module syncRegisterFile(
    	input clk,

        input wr_en, 
        input [1:0] wr_addr,
        input [7:0] wr_data,

        input rdL_en,
        input [1:0] rdL_addr,
        output [7:0] rdL_data,

        input rdR_en,
        input [1:0] rdR_addr,
        output [7:0] rdR_data
);
    
	logic [7:0] D, Q;
	wire [7:0] wr_data_latched;
	logic CLK, OE_N;
    
	hct74574 register(
	.D(wr_data), .Q(wr_data_latched), .CLK(clk), .OE_N(1'b0)
	);
    
    registerFile regFile(
    wr_en,
    wr_addr,
    wr_data_latched,
    rdL_en,
    rdL_addr,
    rdL_data,
    rdR_en,
    rdR_addr,
    rdR_data
    );
    
endmodule

verilog/registerFile/testSync.v
`include "syncRegisterFile.v"
`include "../lib/assertion.v"

`timescale 1ns/100ps
`default_nettype none

module icarus_tb();
    
    logic wr_en;
    logic [1:0] wr_addr;
    logic [7:0] wr_data;
    
    logic rdL_en;
    logic [1:0] rdL_addr;
    logic [7:0] rdL_data;
    
    logic rdR_en;
    logic [1:0] rdR_addr;
    logic [7:0] rdR_data;
    
    logic clk;
    
    syncRegisterFile regFile(
    clk,
    wr_en,
    wr_addr,
    wr_data,
    
    rdL_en,
    rdL_addr,
    rdL_data,
    
    rdR_en,
    rdR_addr,
    rdR_data
    );
    
    
    initial begin
        $dumpfile("dumpfileSync.vcd");
        $dumpvars(0, clk, wr_en, wr_addr, wr_data, rdL_en, rdL_addr, rdL_data, rdR_en, rdR_addr, rdR_data);
        
        $display ("");
        $display ($time, "       _____                       ______                           _____");
        $display ($time, "   clk wr_en wr_addr   wr_data  |  rdL_en   rdL_addr  rdL_data  |   rdR_en  rdR_addr  rdR_data");
        $monitor ($time, "   %1b  %1b          %2b  %8b  |       %1b         %2b  %8b  |        %1b        %2b  %8b",
        clk, wr_en, wr_addr, wr_data, rdL_en, rdL_addr, rdL_data, rdR_en, rdR_addr, rdR_data
        );
    end
    
    initial begin
        parameter disabled       = 1;
        parameter enabled        = 0;
        parameter pulse_disabled = 0;
        parameter pulse_enabled  = 1;
        parameter cycle          = 100;
        
        $display("defaults: write enabled at 0 with 255, no read");
		clk=0;

        wr_en   = enabled;
        wr_addr = 0;
        wr_data = 255;
        
        rdL_en   = disabled;
        rdL_addr = 0;
        
        rdR_en   = disabled;
        rdR_addr = 0;
        
        #cycle;
        `assertEquals(rdL_data, 8'bz);
        `assertEquals(rdR_data, 8'bz);
        
        $display("write enabled at 0 with 1, readL disabled, readR en at 0, but no clock");
        wr_en   = enabled;
        rdL_en  = disabled;
        rdR_en  = enabled;
        wr_data = 1;
        #cycle;
        `assertEquals(rdL_data, 8'bz);
        `assertEquals(rdR_data, 8'dx);

        $display("clock");
		// needs clock to be triggered
		clk=0; #1; clk=1; 
        #cycle;
        `assertEquals(rdL_data, 8'bz);
        `assertEquals(rdR_data, 8'd1);

        $display("clock 255intoboth");
		clk=0; #1; clk=1; 
        wr_en   = enabled;
        rdL_en  = enabled;
        rdR_en  = enabled;
        wr_data = 8'hff;
        #cycle;
        `assertEquals(rdL_data, 8'hff);
        `assertEquals(rdR_data, 8'hff);


        #cycle;
        $finish;
    end
    
endmodule

verilog/registerFile/dumpfileSync.vcd
$date
	Sat Nov  9 13:18:50 2019
$end
$version
	Icarus Verilog
$end
$timescale
	100ps
$end
$scope module icarus_tb $end
$var reg 1 ! clk $end
$upscope $end
$scope module icarus_tb $end
$var reg 1 " wr_en $end
$upscope $end
$scope module icarus_tb $end
$var reg 2 # wr_addr [1:0] $end
$upscope $end
$scope module icarus_tb $end
$var reg 8 $ wr_data [7:0] $end
$upscope $end
$scope module icarus_tb $end
$var reg 1 % rdL_en $end
$upscope $end
$scope module icarus_tb $end
$var reg 2 & rdL_addr [1:0] $end
$upscope $end
$scope module icarus_tb $end
$var wire 8 ' rdL_data [7:0] $end
$upscope $end
$scope module icarus_tb $end
$var reg 1 ( rdR_en $end
$upscope $end
$scope module icarus_tb $end
$var reg 2 ) rdR_addr [1:0] $end
$upscope $end
$scope module icarus_tb $end
$var wire 8 * rdR_data [7:0] $end
$upscope $end
$enddefinitions $end
#0
$dumpvars
bx *
b0 )
1(
bx '
b0 &
1%
b11111111 $
b0 #
0"
0!
$end
#180
bz '
bz *
#1000
b1 $
0(
#1180
bx *
#2010
1!
#2470
b1 *
#3010
0!
#3020
b11111111 $
0%
1!
#3200
b1 '
#3480
b11111111 *
b11111111 '
