verilog/74670/keep/assertion.v
// assertion macro used in tests - is there a built for this??
`define equals(actual, expected, msg) \
if (actual === expected) begin \
  if (1==2) $display("passed :  %d == %d : %s", actual, expected, msg); \
end \
else \
begin  \
  $display("failed : got '%d' when expecting '%d' : %s", actual, expected, msg); 	\
end
 // $finish; \

verilog/74670/hct74670.v
// https://media.digikey.com/pdf/Data%20Sheets/NXP%20PDFs/74HC(T)670.pdf
// active low enable inputs

// NOTE:
// MIN _WE pulsewidth = 20ns   : http://www.ti.com/lit/ds/schs195c/schs195c.pdf?ts=1588009560263
// MIN _WE pulsewidth = 9-18ns : https://media.digikey.com/pdf/Data%20Sheets/NXP%20PDFs/74HC(T)670.pdf

`timescale 1ns/1ns
module hct74670 (input _wr_en,
                 input [1:0] wr_addr,
                 input [3:0] wr_data,
                 input _rd_en,
                 input [1:0] rd_addr,
                 output [3:0] rd_data);
    
    parameter LOG=0;

    localparam PD_RE_TO_Q=18;
    localparam PD_A_TO_Q=21;
    localparam PD_D_TO_Q=27;
    localparam PD_WE_TO_Q=28;

// verilator lint_off UNOPTFLAT
    // Register file storage
    reg [3:0] registers[3:0];
    reg [3:0] tmp_data;

// verilator lint_on UNOPTFLAT

    // necessary to make it possible to set an initial value into REGA so that I can do   NAME=0   
    // or any other operation without X into an ALU input causing an X on the output
    initial begin
        if (LOG) $display("INITIALISING EMPTY REGISTER %m FILE TO VALUES [0,1,2,3]");
        registers[0] = 0;
        registers[1] = 1;
        registers[2] = 2;
        registers[3] = 3;
    end
      
    reg [3:0] out_val;
    
    specify
        (_rd_en *> rd_data)  = PD_RE_TO_Q;
        (_wr_en *> rd_data)  = PD_WE_TO_Q;
        (rd_addr *> rd_data) = PD_A_TO_Q;
        (wr_data => rd_data) = PD_D_TO_Q;
    endspecify
    
    // write to register file
    always @* begin
        if (!_wr_en) begin
            registers[wr_addr] = wr_data;
        end
    end

    always @(registers[0]) begin
            if (LOG) $display("%9t ", $time, ": 74670 setting reg[0]  <= ", registers[0], " : %m");
    end
    always @(registers[1]) begin
            if (LOG) $display("%9t ", $time, ": 74670 setting reg[1]  <= ", registers[1], " : %m");
    end
    always @(registers[2]) begin
            if (LOG) $display("%9t ", $time, ": 74670 setting reg[2]  <= ", registers[2], " : %m");
    end
    always @(registers[3]) begin
            if (LOG) $display("%9t ", $time, ": 74670 setting reg[3]  <= ", registers[3], " : %m");
    end
        
        
    // reading from register file
    always_comb
    // always @(*)  << this gives warning: ./hct74670.v:32: warning: @* is sensitive to all 4 words in array 'registers'.
    begin
        out_val = registers[rd_addr];
    end
    
    assign rd_data = _rd_en ? 4'bz : out_val;
    
endmodule

verilog/74670/test.v
`include "hct74670.v"
`include "../lib/assertion.v"

`timescale 1ns/100ps
`default_nettype none

module icarus_tb();
    
    logic wr_en;
    logic rd_en;
    logic [1:0] wr_addr, rd_addr;
    logic [3:0] wr_data, rd_data;
    
    hct74670 regfile(
    wr_en, wr_addr,  wr_data,
    rd_en, rd_addr,  rd_data
    );
    
    
    initial begin
        $dumpfile("dumpfile.vcd");
        $dumpvars(0,  wr_en, rd_en,   wr_addr, rd_addr, wr_data, rd_data);
        
        $display ("");
        $display ($time,"   %s   %s | %s <= %s  | %s => %s", "wr_en", "rd_en",   "wr_addr", "wr_data", "rd_addr", "rd_data");
        $monitor ($time,"   %5b   %5b | %7b <= %7b  | %7b => %7b", wr_en, rd_en,   wr_addr, wr_data, rd_addr, rd_data);
    end
    
    
    // uncoment to see periodic reports
    //always
    //	#10 $display ($time,"   %5b   %5b %7b < = %7b  out %7b = > %7b", wr_en, rd_en,   wr_addr, wr_data, rd_addr, rd_data);
    
    initial begin
        parameter low      = 1'b0;
        parameter high     = 1'b1;
        parameter enabled  = low;
        parameter disabled = high;
        
        parameter undefined_data = 4'bx;
        parameter zed_data       = 4'bz;
        
        rd_en   = enabled;
        wr_addr = 0;
        wr_data = 10;
        rd_addr = 0;
        #10
        `equals(rd_data , undefined_data, "nothing written so all data should be x");
        
        wr_en = enabled;
        #5
        `equals(rd_data , undefined_data, "nothing written so all data should be x");
        #24
        `equals(rd_data , 10, "write enabled");
        
        wr_data = 1;
        #5
        `equals(rd_data , 10, "write enabled - data changed - output not changed yet");
        #24
        `equals(rd_data , 1, "write enabled and write data changed - should propagate to read");
        
        #5
        
        wr_data = 15;
        wr_en   = disabled;
        #29
        `equals(rd_data , 1, "write disabled - retains value");
        
        wr_en = enabled;
        #29
        `equals(rd_data , 15, "write enabled location 2");
        
        rd_en = disabled;
        #29
        `equals(rd_data , zed_data, "read disabled");
        
        #29
        $finish;
    end
    
    
endmodule

verilog/74670/dumpfile.vcd
$date
	Sat Nov  9 13:15:40 2019
$end
$version
	Icarus Verilog
$end
$timescale
	100ps
$end
$scope module icarus_tb $end
$var reg 1 ! wr_en $end
$upscope $end
$scope module icarus_tb $end
$var reg 1 " rd_en $end
$upscope $end
$scope module icarus_tb $end
$var reg 2 # wr_addr [1:0] $end
$upscope $end
$scope module icarus_tb $end
$var reg 2 $ rd_addr [1:0] $end
$upscope $end
$scope module icarus_tb $end
$var reg 4 % wr_data [3:0] $end
$upscope $end
$scope module icarus_tb $end
$var wire 4 & rd_data [3:0] $end
$upscope $end
$enddefinitions $end
#0
$dumpvars
bx &
b1010 %
b0 $
b0 #
0"
x!
$end
#100
0!
#380
b1010 &
#390
b1 %
#660
b1 &
#730
1!
b1111 %
#1020
0!
#1300
b1111 &
#1310
1"
#1490
bz &
