verilog/74670/keep/assertion.v
// assertion macro used in tests - is there a built for this??
`define equals(actual, expected, msg) \
if (actual === expected) begin \
  if (1==2) $display("passed :  %d == %d : %s", actual, expected, msg); \
end \
else \
begin  \
  $display("failed : got '%d' when expecting '%d' : %s", actual, expected, msg); 	\
end
 // $finish; \

verilog/74670/keep/hct74670.v
// https://media.digikey.com/pdf/Data%20Sheets/NXP%20PDFs/74HC(T)670.pdf
// active low enable inputs

`timescale 1ns/100ps
module hct74670
(
	input wr_en, 
	input [1:0] wr_addr, 
	input [3:0] wr_data, 
	input rd_en,
	input [1:0] rd_addr,
	output [3:0] rd_data
);

// Register file storage
reg [3:0] registers[3:0];

specify
	(rd_en *> rd_data) = (18:18:35);
	(wr_en *> rd_data) = (28:28:50);
	(rd_addr *> rd_data) = (21:21:40);
	(wr_data => rd_data) = (27:27:50);
endspecify

// Read and write from register file
always @(*) begin
	if (!wr_en) begin
		registers[wr_addr] <= wr_data;
	end

	out_val <= registers[rd_addr];
end


reg [7:0] out_val;

assign #(5:5:12, 5:5:12) rd_data = rd_en ? 8'bz : out_val;

endmodule

verilog/74670/keep/test_74670.v
`include "hct74670.v"
`include "assertion.v"

`timescale 1ns/100ps
`default_nettype none

module icarus_tb();

logic wr_en;
logic rd_en;
logic [1:0] wr_addr, rd_addr; 
logic [3:0] wr_data, rd_data; 

hct74670 regfile(
	wr_en, wr_addr,  wr_data, 
	rd_en, rd_addr,  rd_data             
);


initial begin
	$dumpfile("dumpfile.vcd");
	$dumpvars(0,  wr_en, rd_en,   wr_addr, rd_addr, wr_data, rd_data );

	$display ("");
	$display ($time,"   %s   %s %s <= %s  out %s => %s", "wr_en", "rd_en",   "wr_addr", "wr_data", "rd_addr", "rd_data" );
	$monitor ($time,"   %5b   %5b %7b <= %7b  out %7b => %7b", wr_en, rd_en,   wr_addr, wr_data, rd_addr, rd_data );
end


// uncoment to see periodic reports
//always
//	#10 $display ($time,"   %5b   %5b %7b <= %7b  out %7b => %7b", wr_en, rd_en,   wr_addr, wr_data, rd_addr, rd_data );

initial begin
	parameter low = 1'b0;
	parameter high = 1'b1;
	parameter enabled  = low;
	parameter disabled = high;

	parameter undefined_data = 4'bx;
	parameter zed_data = 4'bz;

	rd_en = enabled;
	wr_addr = 0;
	wr_data= 10;
	rd_addr= 0;
	#10      
	`equals(rd_data , undefined_data, "nothing written so all data should be x");

	wr_en = enabled;
	#5
	`equals(rd_data , undefined_data, "nothing written so all data should be x");
	#24
	`equals(rd_data , 10, "write enabled");


	wr_data= 15;
	wr_en = disabled;
	#29
	`equals(rd_data , 10, "write disabled - retains value");

	wr_en = enabled;
	#29
	`equals(rd_data , 15, "write enabled location 2");

	rd_en = disabled;
	#29
	`equals(rd_data , zed_data, "read disabled");

	#29
	$finish;
end


endmodule

verilog/74670/keep/dumpfile.vcd
$date
	Wed Sep 18 22:48:37 2019
$end
$version
	Icarus Verilog
$end
$timescale
	100ps
$end
$scope module icarus_tb $end
$var reg 1 ! wr_en $end
$upscope $end
$scope module icarus_tb $end
$var reg 1 " rd_en $end
$upscope $end
$scope module icarus_tb $end
$var reg 2 # wr_addr [1:0] $end
$upscope $end
$scope module icarus_tb $end
$var reg 2 $ rd_addr [1:0] $end
$upscope $end
$scope module icarus_tb $end
$var reg 4 % wr_data [3:0] $end
$upscope $end
$scope module icarus_tb $end
$var wire 4 & rd_data [3:0] $end
$upscope $end
$enddefinitions $end
#0
$dumpvars
bx &
b1010 %
b0 $
b0 #
0"
x!
$end
#100
0!
#380
b1010 &
#390
1!
b1111 %
#680
0!
#960
b1111 &
#970
1"
#1150
bz &
