verilog/74574/hct74574.v
`ifndef hct74574
`define hct74574

/* Timings from https://assets.nexperia.com/documents/data-sheet/74HC_HCT574.pdf
 * */
`timescale 1ns/100ps
module hct74574 (
input CLK,
input _OE,        // negative enable
input [7:0] D,
output [7:0] Q
);
    parameter LOG=0;

    if (LOG) always @* begin
        $display("%9t", $time, " LATCH %m  CLK=%1b _OE=%1b D=%08b Q=%08b", CLK, _OE, D, Q);
    end

    reg [8:0] data;
    
    specify
    (CLK *> Q) = (15);
    (_OE *> Q) = (19);
    endspecify
    
    always @(posedge CLK)
        data <= D;
    
    assign #(19) Q = _OE ? 8'bz: data;
    
endmodule

`endif

verilog/74574/test.v
`include "hct74574.v"
`include "../lib/assertion.v"

`timescale 1ns/100ps
`default_nettype none

module icarus_tb();
    
	logic [7:0] D, Q;
	logic CLK, OE_N;
    
	hct74574 register(
	.D, .Q,
	.CLK, .OE_N
	);
    
    
    initial begin
        $dumpfile("dumpfile.vcd");
        $dumpvars(0,  D, Q, CLK, OE_N);
        
        $display ("");
        $display ($time, "   D         Q         CLK  OE_N");
        $monitor ($time, "   %8b  %8b  %b   %b", D,   Q,   CLK,  OE_N);
    end

    initial begin
        parameter zero      = 8'b0;
        parameter aa     = 8'b10101010;
        parameter undefined = 8'bx;
        parameter zed       = 8'bz;
        parameter low  = 0;
        parameter high  = 1;
        parameter disabled = 1;
        parameter enabled = 0;
        parameter tPD = 19+1;

	D=zero;
	CLK=low;
	#tPD 
        `equals(Q , undefined, "initial");

	OE_N=disabled;
	#tPD 
        `equals(Q , zed, "output disabled");

	OE_N=enabled;
	#tPD 
        `equals(Q , undefined, "unclocked - D = X");

	D=aa;
	CLK=high;
	#10
        `equals(Q , undefined, "clocked - but not yet propagated");

	D=1;
	CLK=high;
	#tPD
        `equals(Q , aa, "transition to high - wth AA");

	D=255;
	#tPD
        `equals(Q , aa, "remain high - wth 255");

	D=zero;
	CLK=low;
	#tPD
        `equals(Q , aa, "transition to low - wth zero");

	D=255;
	CLK=high;
	OE_N=disabled;
	#tPD
        `equals(Q , zed, "transition to high - wth 255 but OE disabled");

	OE_N=enabled;
	#tPD
        `equals(Q , 255, "oe enabled");


    end
endmodule

verilog/74574/dumpfile.vcd
$date
	Thu Mar 19 23:28:32 2020
$end
$version
	Icarus Verilog
$end
$timescale
	100ps
$end
$scope module icarus_tb $end
$var reg 8 ! D [7:0] $end
$upscope $end
$scope module icarus_tb $end
$var wire 8 " Q [7:0] $end
$upscope $end
$scope module icarus_tb $end
$var reg 1 # CLK $end
$upscope $end
$scope module icarus_tb $end
$var reg 1 $ OE_N $end
$upscope $end
$enddefinitions $end
#0
$dumpvars
x$
0#
bx "
b0 !
$end
#200
1$
#390
bz "
#400
0$
#590
bx "
#600
1#
b10101010 !
#700
b1 !
#790
b10101010 "
#900
b11111111 !
#1100
0#
b0 !
#1300
1$
1#
b11111111 !
#1490
bz "
#1500
0$
#1690
b11111111 "
