verilog/74573/hct74573.v
/* octal d-type transparent latch
 Same model as 74373.
 
 LE = H is transparent
 OE_N = H is Z
 
 Timings have are for 74HCT573
 https://assets.nexperia.com/documents/data-sheet/74HC_HCT573.pdf
 https://assets.nexperia.com/documents/data-sheet/74HC_HCT373.pdf
 */

`timescale 1ns/100ps
module hct74573 (input D0,
                 input D1,
                 input D2,
                 input D3,
                 input D4,
                 input D5,
                 input D6,
                 input D7,
                 output Q0,
                 output Q1,
                 output Q2,
                 output Q3,
                 output Q4,
                 output Q5,
                 output Q6,
                 output Q7,
                 input LE,
                 input OE_N);
    
    reg q0, q1, q2, q3, q4, q5, q6, q7;
    
    // X is initial state of Q
    //initial
    //    {q0, q1, q2, q3, q4, q5, q6, q7} <= 8'b0;
    
    specify
    (D0 => Q0) = (17);
    (D1 => Q1) = (17);
    (D2 => Q2) = (17);
    (D3 => Q3) = (17);
    (D4 => Q4) = (17);
    (D5 => Q5) = (17);
    (D6 => Q6) = (17);
    (D7 => Q7) = (17);
    
    (LE => Q0) = (15);
    (LE => Q1) = (15);
    (LE => Q2) = (15);
    (LE => Q3) = (15);
    (LE => Q4) = (15);
    (LE => Q5) = (15);
    (LE => Q6) = (15);
    (LE => Q7) = (15);
    
    (OE_N => Q0) = (18);
    (OE_N => Q1) = (18);
    (OE_N => Q2) = (18);
    (OE_N => Q3) = (18);
    (OE_N => Q4) = (18);
    (OE_N => Q5) = (18);
    (OE_N => Q6) = (18);
    (OE_N => Q7) = (18);
    
    endspecify
    
    always @(D0 or D1 or D2 or D3 or D4 or D5 or D6 or D7 or LE)
        if (LE)
        begin
            {q0,q1,q2,q3,q4,q5,q6,q7} <= {D0,D1,D2,D3,D4,D5,D6,D7};
        end
    
    assign Q0 = OE_N ? 1'bz : q0;
    assign Q1 = OE_N ? 1'bz : q1;
    assign Q2 = OE_N ? 1'bz : q2;
    assign Q3 = OE_N ? 1'bz : q3;
    assign Q4 = OE_N ? 1'bz : q4;
    assign Q5 = OE_N ? 1'bz : q5;
    assign Q6 = OE_N ? 1'bz : q6;
    assign Q7 = OE_N ? 1'bz : q7;
    
endmodule

verilog/74573/test_74573.v
`include "hct74573.v"
`include "../lib/assertion.v"

`timescale 1ns/100ps
`default_nettype none

module icarus_tb();
    
	logic D0, D1, D2, D3, D4, D5, D6, D7;
	logic Q0, Q1, Q2, Q3, Q4, Q5, Q6, Q7;
	logic LE, OE_N;
    
	hct74573 latch(
	.D0, .D1, .D2, .D3, .D4, .D5, .D6, .D7,
	.Q0, .Q1, .Q2, .Q3, .Q4, .Q5, .Q6, .Q7,
	.LE, .OE_N
	);
    
    
    initial begin
        $dumpfile("dumpfile.vcd");
        $dumpvars(0,  
		D0, D1, D2, D3, D4, D5, D6, D7,
		Q0, Q1, Q2, Q3, Q4, Q5, Q6, Q7,
		LE, OE_N
	);
        
        $display ("");
        $display ($time, "   D0 D1 D2 D3 D4 D5 D6 D7   Q0 Q1 Q2 Q3 Q4 Q5 Q6 Q7   LE  OE_N");
        $monitor ($time, "   %d  %d  %d  %d  %d  %d  %d  %d    %d  %d  %d  %d  %d  %d  %d  %d    %d   %d",
		D0, D1, D2, D3, D4, D5, D6, D7,   Q0, Q1, Q2, Q3, Q4, Q5, Q6, Q7,   LE,  OE_N
	);
    end

    initial begin
        parameter low      = 1'b0;
        parameter high     = 1'b1;
        parameter undefined = 1'bx;
        parameter zed       = 1'bz;

        parameter latched  = low;
        parameter transparent  = high;

        parameter disabled = high;
        parameter enabled = low;
        

	D0=low;
	#30 
        `equals(Q0 , undefined, "initial");

	OE_N=disabled;
	LE=transparent;
	#16 
        `equals(Q0 , zed, "latch transparent - output enabled");

	OE_N=enabled;
	#19 
        `equals(Q0 , low, "latch transparent - D0 low");

	D0=high;
	#18
        `equals(Q0 , high, "D0 high");

	LE=latched;
	D0=low;
	#50
        `equals(Q0 , high, "D0 high because latched");

	LE=transparent;
	#16
        `equals(Q0 , low, "D0 low because transparent");

	OE_N=disabled;
	#19
        `equals(Q0 , zed, "D0 low because transparent");

    end
endmodule

verilog/74573/dumpfile.vcd
$date
	Thu Sep 19 03:10:45 2019
$end
$version
	Icarus Verilog
$end
$timescale
	100ps
$end
$scope module icarus_tb $end
$var reg 1 ! D0 $end
$upscope $end
$scope module icarus_tb $end
$var reg 1 " D1 $end
$upscope $end
$scope module icarus_tb $end
$var reg 1 # D2 $end
$upscope $end
$scope module icarus_tb $end
$var reg 1 $ D3 $end
$upscope $end
$scope module icarus_tb $end
$var reg 1 % D4 $end
$upscope $end
$scope module icarus_tb $end
$var reg 1 & D5 $end
$upscope $end
$scope module icarus_tb $end
$var reg 1 ' D6 $end
$upscope $end
$scope module icarus_tb $end
$var reg 1 ( D7 $end
$upscope $end
$scope module icarus_tb $end
$var wire 1 ) Q0 $end
$upscope $end
$scope module icarus_tb $end
$var wire 1 * Q1 $end
$upscope $end
$scope module icarus_tb $end
$var wire 1 + Q2 $end
$upscope $end
$scope module icarus_tb $end
$var wire 1 , Q3 $end
$upscope $end
$scope module icarus_tb $end
$var wire 1 - Q4 $end
$upscope $end
$scope module icarus_tb $end
$var wire 1 . Q5 $end
$upscope $end
$scope module icarus_tb $end
$var wire 1 / Q6 $end
$upscope $end
$scope module icarus_tb $end
$var wire 1 0 Q7 $end
$upscope $end
$scope module icarus_tb $end
$var reg 1 1 LE $end
$upscope $end
$scope module icarus_tb $end
$var reg 1 2 OE_N $end
$upscope $end
$enddefinitions $end
#0
$dumpvars
x2
x1
x0
x/
x.
x-
x,
x+
x*
x)
x(
x'
x&
x%
x$
x#
x"
0!
$end
#300
11
12
#450
z)
z*
z+
z,
z-
z.
z/
z0
#460
02
#640
0)
x*
x+
x,
x-
x.
x/
x0
#650
1!
#820
1)
#830
0!
01
#1330
11
#1480
0)
#1490
12
#1670
z)
z*
z+
z,
z-
z.
z/
z0
