verilog/74573/hct74573.v
/* octal d-type transparent latch.
 Same model as 74373 but with timings from HCT573
 
 LE = H is transparent
 OE_N = H is Z
 
 Timings have are for 74HCT573
 https://assets.nexperia.com/documents/data-sheet/74HC_HCT573.pdf
 https://assets.nexperia.com/documents/data-sheet/74HC_HCT373.pdf
 */

`timescale 1ns/100ps
module hct74573 (
    input LE,
    input OE_N,
	input [7:0] D,
    output [7:0] Q
);
    
    reg [7:0] data;
    
    specify
    (D => Q) = (17);
    (LE *> Q) = (15);
    (OE_N *> Q) = (18);
    endspecify
    
    always @(D or LE)
        if (LE)
        begin
            data <= D;
        end
    
    assign Q = OE_N ? 8'bz : data;
    
endmodule

verilog/74573/test.v
`include "hct74573.v"
`include "../lib/assertion.v"

`timescale 1ns/100ps
`default_nettype none

module icarus_tb();
    
	logic [7:0] D, Q;
	logic LE, OE_N;
    
	hct74573 latch(
	.D, .Q,
	.LE, .OE_N
	);
    
    
    initial begin
        $dumpfile("dumpfile.vcd");
        $dumpvars(0,  D, Q, LE, OE_N);
        
        $display ("");
        $display ($time, "   D         Q         LE  OE_N");
        $monitor ($time, "   %8b  %8b  %b   %b", D,   Q,   LE,  OE_N);
    end

    initial begin
        parameter zero      = 8'b0;
        parameter aa     = 8'b10101010;
        parameter undefined = 8'bx;
        parameter zed       = 8'bz;

        parameter latched  = 0;
        parameter transparent  = 1;

        parameter disabled = 1;
        parameter enabled = 0;
        

	D=zero;
	#30 
        `equals(Q , undefined, "initial");

	OE_N=disabled;
	LE=transparent;
	#16 
        `equals(Q , zed, "latch transparent - output enabled");

	OE_N=enabled;
	#19 
        `equals(Q , zero, "latch transparent - D0 zero");

	D=aa;
	#18
        `equals(Q , aa, "D0 0xAA");

	LE=latched;
	D=zero;
	#50
        `equals(Q , aa, "D0 0xAA because latched");

	LE=transparent;
	#16
        `equals(Q , zero, "D0 zero because transparent");

	OE_N=disabled;
	#19
        `equals(Q , zed, "D0 zero because transparent");

    end
endmodule

verilog/74573/dumpfile.vcd
$date
	Sat Nov  9 13:14:29 2019
$end
$version
	Icarus Verilog
$end
$timescale
	100ps
$end
$scope module icarus_tb $end
$var reg 8 ! D [7:0] $end
$upscope $end
$scope module icarus_tb $end
$var wire 8 " Q [7:0] $end
$upscope $end
$scope module icarus_tb $end
$var reg 1 # LE $end
$upscope $end
$scope module icarus_tb $end
$var reg 1 $ OE_N $end
$upscope $end
$enddefinitions $end
#0
$dumpvars
x$
x#
bx "
b0 !
$end
#300
1#
1$
#450
bz "
#460
0$
#640
b0 "
#650
b10101010 !
#820
b10101010 "
#830
b0 !
0#
#1330
1#
#1480
b0 "
#1490
1$
#1670
bz "
